moneyflow/__init__.py
moneyflow/__main__.py
moneyflow/account_manager.py
moneyflow/amazon_linker.py
moneyflow/app.py
moneyflow/app_controller.py
moneyflow/backend_config.py
moneyflow/cache_manager.py
moneyflow/cache_orchestrator.py
moneyflow/categories.py
moneyflow/cli.py
moneyflow/commit_orchestrator.py
moneyflow/credentials.py
moneyflow/data_manager.py
moneyflow/demo_data_generator.py
moneyflow/duplicate_detector.py
moneyflow/formatters.py
moneyflow/keybindings.py
moneyflow/logging_config.py
moneyflow/migration.py
moneyflow/modal_helper.py
moneyflow/monarchmoney.py
moneyflow/notification_helper.py
moneyflow/retry_logic.py
moneyflow/state.py
moneyflow/textual_view.py
moneyflow/theme_manager.py
moneyflow/time_navigator.py
moneyflow/version.py
moneyflow/view_interface.py
moneyflow/ynab_client.py
moneyflow/backends/__init__.py
moneyflow/backends/amazon.py
moneyflow/backends/base.py
moneyflow/backends/demo.py
moneyflow/backends/monarch.py
moneyflow/backends/ynab.py
moneyflow/importers/__init__.py
moneyflow/importers/amazon_orders_csv.py
moneyflow/screens/__init__.py
moneyflow/screens/account_name_input_screen.py
moneyflow/screens/account_selector_screen.py
moneyflow/screens/batch_scope_screen.py
moneyflow/screens/budget_selector_screen.py
moneyflow/screens/credential_screens.py
moneyflow/screens/duplicates_screen.py
moneyflow/screens/edit_screens.py
moneyflow/screens/review_screen.py
moneyflow/screens/search_screen.py
moneyflow/screens/transaction_detail_screen.py
moneyflow/styles/moneyflow.tcss
moneyflow/styles/themes/berg.tcss
moneyflow/styles/themes/default.tcss
moneyflow/styles/themes/dracula.tcss
moneyflow/styles/themes/gruvbox.tcss
moneyflow/styles/themes/monokai.tcss
moneyflow/styles/themes/nord.tcss
moneyflow/styles/themes/solarized-dark.tcss
moneyflow/widgets/__init__.py
moneyflow/widgets/help_screen.py
moneyflow-0.8.1.dist-info/METADATA
moneyflow-0.8.1.dist-info/WHEEL
moneyflow-0.8.1.dist-info/entry_points.txt
moneyflow-0.8.1.dist-info/licenses/LICENSE
moneyflow-0.8.1.dist-info/RECORD
