Metadata-Version: 2.4
Name: moneyflow
Version: 0.8.1
Summary: Track your moneyflow - A powerful terminal UI for personal finance management
Project-URL: Homepage, https://github.com/wesm/moneyflow
Project-URL: Repository, https://github.com/wesm/moneyflow
Project-URL: Issues, https://github.com/wesm/moneyflow/issues
Author-email: Wes McKinney <info@wesmckinney.com>
Maintainer-email: Wes McKinney <info@wesmckinney.com>
License: MIT License
License-File: LICENSE
Keywords: budget,cashflow,finance,monarch-money,personal-finance,terminal,transactions,tui
Classifier: Development Status :: 3 - Alpha
Classifier: Environment :: Console
Classifier: Intended Audience :: End Users/Desktop
Classifier: License :: OSI Approved :: MIT License
Classifier: Programming Language :: Python :: 3
Classifier: Programming Language :: Python :: 3.11
Classifier: Programming Language :: Python :: 3.12
Classifier: Programming Language :: Python :: 3.13
Classifier: Topic :: Office/Business :: Financial
Classifier: Topic :: Terminals
Requires-Python: >=3.11
Requires-Dist: aiohttp>=3.8.4
Requires-Dist: click<8.3.0,>=8.1.0
Requires-Dist: cryptography>=41.0.0
Requires-Dist: gql>=3.4
Requires-Dist: oathtool>=2.3.1
Requires-Dist: polars>=0.19.0
Requires-Dist: python-dateutil>=2.8.0
Requires-Dist: pyyaml>=6.0
Requires-Dist: textual>=0.47.0
Requires-Dist: ynab>=1.9.0
